MANIFEST.in
setup.py
Products/__init__.py
Products.SilvaExternalSources.egg-info/PKG-INFO
Products.SilvaExternalSources.egg-info/SOURCES.txt
Products.SilvaExternalSources.egg-info/dependency_links.txt
Products.SilvaExternalSources.egg-info/entry_points.txt
Products.SilvaExternalSources.egg-info/namespace_packages.txt
Products.SilvaExternalSources.egg-info/not-zip-safe
Products.SilvaExternalSources.egg-info/requires.txt
Products.SilvaExternalSources.egg-info/top_level.txt
Products/SilvaExternalSources/CREDITS.txt
Products/SilvaExternalSources/CSVSource.py
Products/SilvaExternalSources/CodeSource.py
Products/SilvaExternalSources/CodeSourceService.py
Products/SilvaExternalSources/ExternalSource.py
Products/SilvaExternalSources/HISTORY.txt
Products/SilvaExternalSources/LICENSE.txt
Products/SilvaExternalSources/README.txt
Products/SilvaExternalSources/SQLSource.py
Products/SilvaExternalSources/SourceAsset.py
Products/SilvaExternalSources/__init__.py
Products/SilvaExternalSources/configure.zcml
Products/SilvaExternalSources/errors.py
Products/SilvaExternalSources/ftesting.zcml
Products/SilvaExternalSources/interfaces.py
Products/SilvaExternalSources/patches.py
Products/SilvaExternalSources/testing.py
Products/SilvaExternalSources/CodeSourceService_templates/configureexisting.cpt
Products/SilvaExternalSources/CodeSourceService_templates/configureinstall.cpt
Products/SilvaExternalSources/CodeSourceService_templates/manageexistingcodesources.pt
Products/SilvaExternalSources/CodeSourceService_templates/manageinstallcodesources.pt
Products/SilvaExternalSources/CodeSourceService_templates/managesourceserrors.pt
Products/SilvaExternalSources/codesources/__init__.py
Products/SilvaExternalSources/codesources/api.py
Products/SilvaExternalSources/codesources/googlemaps.py
Products/SilvaExternalSources/codesources/make_HTML_token.py
Products/SilvaExternalSources/codesources/toc.py
Products/SilvaExternalSources/codesources/youtube.py
Products/SilvaExternalSources/codesources/cs_citation/LICENSE.txt
Products/SilvaExternalSources/codesources/cs_citation/README.txt
Products/SilvaExternalSources/codesources/cs_citation/icon.png
Products/SilvaExternalSources/codesources/cs_citation/parameters.xml
Products/SilvaExternalSources/codesources/cs_citation/render_citation.pt
Products/SilvaExternalSources/codesources/cs_citation/source.ini
Products/SilvaExternalSources/codesources/cs_citation/ustr.py
