Metadata-Version: 1.1
Name: Products.SilvaExternalSources
Version: 3.0.3
Summary: Externals content sources to embed in Silva CMS
Home-page: https://github.com/silvacms/Products.SilvaExternalSources
Author: Infrae
Author-email: info@infrae.com
License: BSD
Keywords: silva cms document external sources
Platform: UNKNOWN
Classifier: Framework :: Zope2
Classifier: License :: OSI Approved :: BSD License
Classifier: Programming Language :: Python
Classifier: Topic :: Software Development :: Libraries :: Python Modules
